jellyplex/__init__.py
jellyplex/cli.py
jellyplex/config.py
jellyplex/logging.py
jellyplex/models.py
jellyplex/session.py
jellyplex/tools/__init__.py
jellyplex/tools/sync_posters.py
jellyplex/types.py
jellyplex/utils.py
jellyplex-0.1.0a0.dist-info/LICENSE
jellyplex-0.1.0a0.dist-info/METADATA
jellyplex-0.1.0a0.dist-info/WHEEL
jellyplex-0.1.0a0.dist-info/entry_points.txt
jellyplex-0.1.0a0.dist-info/RECORD
