Metadata-Version: 2.1
Name: jellyplex
Version: 0.1.0a0
Summary: Miscellaneous tools for migrating from Plex to Jellyfin
Home-page: https://github.com/janw/jellyplex
License: Apache-2.0
Author: Jan Willhaus
Author-email: mail@janwillhaus.de
Requires-Python: >=3.10,<4.0
Classifier: Development Status :: 4 - Beta
Classifier: Environment :: Console
Classifier: License :: OSI Approved :: Apache Software License
Classifier: Programming Language :: Python :: 3
Classifier: Programming Language :: Python :: 3.10
Classifier: Programming Language :: Python :: 3.11
Classifier: Programming Language :: Python :: 3.12
Classifier: Programming Language :: Python :: 3.13
Classifier: Topic :: Utilities
Requires-Dist: feedparser (>=6.0.10,<7.0.0)
Requires-Dist: platformdirs (>=3.4,<5.0)
Requires-Dist: plexapi (>=4.15.16,<5.0.0)
Requires-Dist: pydantic (>=2.5.3,<3.0.0)
Requires-Dist: pydantic-settings (>=2.5.2,<3.0.0)
Requires-Dist: python-slugify (>=8.0.1,<9.0.0)
Requires-Dist: pyyaml (>=6.0,<7.0)
Requires-Dist: requests (>=2.32.3,<3.0.0)
Requires-Dist: rich-click (>=1.8.0,<2.0.0)
Requires-Dist: tqdm (>=4.66.4,<5.0.0)
Project-URL: Bug Reports, https://github.com/janw/jellyplex/issues
Project-URL: Repository, https://github.com/janw/jellyplex
